lochness/__init__.py
lochness/__version__.py
lochness/beiwe/__init__.py
lochness/config/__init__.py
lochness/daemon/__init__.py
lochness/dropbox/__init__.py
lochness/dropbox/baker.py
lochness/dropbox/cbsn.py
lochness/dropbox/hash.py
lochness/dropbox/mclean.py
lochness/dropbox/multisense.py
lochness/dropbox/nrg.py
lochness/email/__init__.py
lochness/email/template.html
lochness/functools/__init__.py
lochness/hdd/__init__.py
lochness/hdd/buckner.py
lochness/hdd/coombs.py
lochness/icognition/__init__.py
lochness/keyring/__init__.py
lochness/net/__init__.py
lochness/onlinescoring/__init__.py
lochness/redcap/__init__.py
lochness/scheduler/__init__.py
lochness/ssh/__init__.py
lochness/tree/__init__.py
lochness/xnat/__init__.py
lochness-0.15a0.data/scripts/phoenix-generator.py
lochness-0.15a0.data/scripts/sync.py
lochness-0.15a0.dist-info/DESCRIPTION.rst
lochness-0.15a0.dist-info/METADATA
lochness-0.15a0.dist-info/RECORD
lochness-0.15a0.dist-info/WHEEL
lochness-0.15a0.dist-info/metadata.json
lochness-0.15a0.dist-info/top_level.txt
